README.md
setup.py
htmd_pdb2pqr.egg-info/PKG-INFO
htmd_pdb2pqr.egg-info/SOURCES.txt
htmd_pdb2pqr.egg-info/dependency_links.txt
htmd_pdb2pqr.egg-info/entry_points.txt
htmd_pdb2pqr.egg-info/top_level.txt
pdb2pqr/AUTHORS
pdb2pqr/AppService_client.py
pdb2pqr/AppService_services.py
pdb2pqr/AppService_services_types.py
pdb2pqr/AppService_types.py
pdb2pqr/COPYING
pdb2pqr/NEWS
pdb2pqr/README.md
pdb2pqr/SConscript-error.py
pdb2pqr/SConscript-install.py
pdb2pqr/SConscript-main.py
pdb2pqr/__init__.py
pdb2pqr/apbs_cgi.py
pdb2pqr/build_config.py
pdb2pqr/dx2cube.py
pdb2pqr/fabfile.py
pdb2pqr/fabfile_settings.py
pdb2pqr/main.py
pdb2pqr/main_cgi.py
pdb2pqr/pka.py
pdb2pqr/querystatus.py
pdb2pqr/visualize.py
pdb2pqr/visualize2.py
pdb2pqr/dat/AA.xml
pdb2pqr/dat/AMBER.DAT
pdb2pqr/dat/AMBER.names
pdb2pqr/dat/CHARMM.DAT
pdb2pqr/dat/CHARMM.names
pdb2pqr/dat/HYDROGENS.xml
pdb2pqr/dat/NA.xml
pdb2pqr/dat/PARSE.DAT
pdb2pqr/dat/PARSE.names
pdb2pqr/dat/PATCHES.xml
pdb2pqr/dat/PEOEPB.DAT
pdb2pqr/dat/PEOEPB.names
pdb2pqr/dat/SWANSON.DAT
pdb2pqr/dat/SWANSON.names
pdb2pqr/dat/TOPOLOGY.xml
pdb2pqr/dat/TYL06.DAT
pdb2pqr/dat/TYL06.names
pdb2pqr/extensions/__init__.py
pdb2pqr/extensions/chi.py
pdb2pqr/extensions/contact.py
pdb2pqr/extensions/hbond.py
pdb2pqr/extensions/newresinter.py
pdb2pqr/extensions/rama.py
pdb2pqr/extensions/resinter.py
pdb2pqr/extensions/salt.py
pdb2pqr/extensions/summary.py
pdb2pqr/pdb2pka/NEWligand_topology.py
pdb2pqr/pdb2pka/__init__.py
pdb2pqr/pdb2pka/apbs.py
pdb2pqr/pdb2pka/charge_mon.py
pdb2pqr/pdb2pka/example.py
pdb2pqr/pdb2pka/inputgen_pKa.py
pdb2pqr/pdb2pka/ligand_topology.py
pdb2pqr/pdb2pka/pKaIO_compat.py
pdb2pqr/pdb2pka/pKa_base.py
pdb2pqr/pdb2pka/pKa_utility_functions_compat.py
pdb2pqr/pdb2pka/pMC_mult.py
pdb2pqr/pdb2pka/pka_help.py
pdb2pqr/pdb2pka/pka_old.py
pdb2pqr/pdb2pka/pka_routines.py
pdb2pqr/pdb2pka/prepare_pKa_ligand.py
pdb2pqr/propka30/__init__.py
pdb2pqr/propka30/compare.py
pdb2pqr/propka30/experiment.py
pdb2pqr/propka30/propka.py
pdb2pqr/propka30/propka_det.py
pdb2pqr/propka30/propka_gui.py
pdb2pqr/propka30/propka_mut.py
pdb2pqr/propka30/propka_pdb.py
pdb2pqr/src/__init__.py
pdb2pqr/src/aa.py
pdb2pqr/src/definitions.py
