Metadata-Version: 1.0
Name: htmd-pdb2pqr
Version: 0.0.2
Summary: PDB2PQR: an automated pipeline for the setup of Poisson-Boltzmann electrostatics calculations
Home-page: http://www.poissonboltzmann.org/
Author: UNKNOWN
Author-email: UNKNOWN
License: BSD
Platform: UNKNOWN
